config_guiosoft/__init__.py
config_guiosoft/config_class.py
config_guiosoft/config_type.py
config_guiosoft/data_types.py
config_guiosoft/default_value.py
config_guiosoft/exceptions.py
config_guiosoft/logger.py
config_guiosoft/validation_key.py
tests/__init__.py
tests/test_attr.py
tests/test_config.py
tests/test_config_type.py
tests/test_data_types.py
tests/test_default_value.py
tests/test_validation_key.py
config_guiosoft-0.1.5.dist-info/LICENSE
config_guiosoft-0.1.5.dist-info/METADATA
config_guiosoft-0.1.5.dist-info/WHEEL
config_guiosoft-0.1.5.dist-info/top_level.txt
config_guiosoft-0.1.5.dist-info/RECORD
