Metadata-Version: 2.1
Name: config-guiosoft
Version: 0.1.5
Summary: Guiosoft Python Configuration Class
Home-page: UNKNOWN
Author: Guionardo Furlan
Author-email: guionardo@gmail.com
License: UNKNOWN
Project-URL: Documentation, https://github.com/guionardo/py-config/wiki
Project-URL: Source, https://github.com/guionardo/py-config
Platform: UNKNOWN
Classifier: Programming Language :: Python :: 3
Classifier: License :: OSI Approved :: MIT License
Classifier: Operating System :: OS Independent
Classifier: Development Status :: 4 - Beta
Classifier: Intended Audience :: Developers
Requires-Python: >=3.7
Requires-Dist: python-dotenv (==0.14.0)
Requires-Dist: python-dateutil (==2.8.1)
